README.md
setup.cfg
setup.py
PasteBunny/Api.py
PasteBunny/Client.py
PasteBunny/Constants.py
PasteBunny/Models.py
PasteBunny/__init__.py
PasteBunny.egg-info/PKG-INFO
PasteBunny.egg-info/SOURCES.txt
PasteBunny.egg-info/dependency_links.txt
PasteBunny.egg-info/requires.txt
PasteBunny.egg-info/top_level.txt