Metadata-Version: 1.1
Name: PasteBunny
Version: 0.180331a0
Summary: Pastebin wrapper made by bunnies, for bunnies...
Home-page: https://github.com/tmjvonboss/PasteBunny.git
Author: BUNNY TMJ
Author-email: tmukkuroj1337@gmail.com
License: Bunny Licensse
Keywords: PasteBunny
Platform: UNKNOWN
Classifier: Development Status :: 2 - Pre-Alpha
Classifier: Intended Audience :: Developers
Classifier: Programming Language :: Python :: 3
Classifier: Programming Language :: Python :: 3.1
Classifier: Programming Language :: Python :: 3.2
Classifier: Programming Language :: Python :: 3.3
Classifier: Programming Language :: Python :: 3.4
Classifier: Programming Language :: Python :: 3.5
Classifier: Programming Language :: Python :: 3.6
Classifier: Programming Language :: Python :: Implementation :: CPython
Classifier: Programming Language :: Python :: Implementation :: PyPy
Classifier: Topic :: Software Development :: Libraries :: Python Modules
Classifier: Topic :: Internet :: WWW/HTTP :: Dynamic Content
